aion_torch/__init__.py
aion_torch/adapters.py
aion_torch/aion_adapter.py
aion_torch/alpha.py
aion_torch/energy.py
aion_torch/registry.py
aion_torch-0.2.0.dist-info/licenses/LICENSE
aion_torch-0.2.0.dist-info/METADATA
aion_torch-0.2.0.dist-info/WHEEL
aion_torch-0.2.0.dist-info/top_level.txt
aion_torch-0.2.0.dist-info/RECORD
