Metadata-Version: 2.4
Name: aion-torch
Version: 0.2.0
Summary: Adaptive Input/Output Normalization for deep neural networks. Enables stable training of extremely deep networks through adaptive residual scaling (Alpha) by Babayev's Theory
Author: Abbasagha Babayev
License-Expression: MIT
Project-URL: Homepage, https://github.com/Croxus-Labs/aion-torch
Project-URL: Repository, https://github.com/Croxus-Labs/aion-torch
Project-URL: Issues, https://github.com/Croxus-Labs/aion-torch/issues
Project-URL: Documentation, https://github.com/Croxus-Labs/aion-torch#readme
Keywords: deep-learning,normalization,pytorch,residual-connections
Classifier: Development Status :: 3 - Alpha
Classifier: Intended Audience :: Science/Research
Classifier: Programming Language :: Python :: 3
Classifier: Programming Language :: Python :: 3.10
Classifier: Programming Language :: Python :: 3.11
Classifier: Programming Language :: Python :: 3.12
Classifier: Topic :: Scientific/Engineering :: Artificial Intelligence
Requires-Python: >=3.10
License-File: LICENSE
Requires-Dist: torch>=2.0.0
Provides-Extra: dev
Requires-Dist: pytest>=7.0; extra == "dev"
Requires-Dist: pytest-cov>=4.0; extra == "dev"
Requires-Dist: black>=23.0; extra == "dev"
Requires-Dist: ruff>=0.1.0; extra == "dev"
Requires-Dist: pre-commit>=3.0.0; extra == "dev"
Requires-Dist: mypy>=1.0.0; extra == "dev"
Provides-Extra: bench
Requires-Dist: matplotlib>=3.5; extra == "bench"
Requires-Dist: pandas>=1.5; extra == "bench"
Dynamic: license-file
